{
  "bfa7ebd3-b54e-4c37-ab1a-b94764144136": {
    "documents": [],
    "models": [
      {
        "modelId": "1d5865c8-624f-4824-a1d7-b7f7ee40db44",
        "name": "Model_3",
        "status": "generated",
        "words": 131,
        "chars": 894
      }
    ]
  },
  "091b98f2-ea86-4fdb-8b26-1c4b9917da29": {
    "documents": [
      {
        "id": "0f61e255-9b8b-43d1-bd51-9d874302b8ce",
        "name": "01.2 Research Questions.md",
        "chars": 19831,
        "words": 2792
      }
    ],
    "models": [
      {
        "modelId": "50743859-07f7-4f4a-9536-d07901ef19ba",
        "name": "Model_1",
        "status": "generated",
        "words": 37,
        "chars": 290
      },
      {
        "modelId": "5280c43d-d566-4dc0-89f4-d95b48b3e0d1",
        "name": "Model_2",
        "status": "generated",
        "words": 41,
        "chars": 304
      },
      {
        "modelId": "3dc90885-0185-45f8-b1a0-36212be96070",
        "name": "Model_3",
        "status": "generated",
        "words": 48,
        "chars": 310
      },
      {
        "modelId": "08268e19-aa61-4d6d-ad7c-409a30a0f9fc",
        "name": "Model_4",
        "status": "generated",
        "words": 15,
        "chars": 101
      },
      {
        "modelId": "68edfb7b-c2db-4894-8f73-ecae86b9bd6b",
        "name": "Model_5",
        "status": "generated",
        "words": 42,
        "chars": 299
      },
      {
        "modelId": "f0bbaa0a-145a-4716-bc37-0b7ff1f541aa",
        "name": "Model_6",
        "status": "generated",
        "words": 30,
        "chars": 207
      },
      {
        "modelId": "03f922d9-bd4a-45da-9f8f-8098c72deb4a",
        "name": "Model_7",
        "status": "generated",
        "words": 13,
        "chars": 100
      },
      {
        "modelId": "5c7a1007-c85c-41be-a96f-e5a5181c7580",
        "name": "Model_8",
        "status": "generated",
        "words": 26,
        "chars": 196
      },
      {
        "modelId": "7e0c54d9-8c04-4ce7-833b-a97618bbfe45",
        "name": "Model_9",
        "status": "generated",
        "words": 2,
        "chars": 9
      },
      {
        "modelId": "0af71a85-78c0-40be-87b7-9bfe9830d16b",
        "name": "Model_10",
        "status": "generated",
        "words": 26,
        "chars": 195
      }
    ]
  }
}